tangoctl/__init__.py
tangoctl/__main__.py
tangoctl/cli.py
tangoctl/tangoctl.py
tangoctl-0.2.3.dist-info/METADATA
tangoctl-0.2.3.dist-info/RECORD
tangoctl-0.2.3.dist-info/WHEEL
tangoctl-0.2.3.dist-info/entry_points.txt
tangoctl-0.2.3.dist-info/top_level.txt
