Metadata-Version: 2.1
Name: tangoctl
Version: 0.2.3
Summary: tango system cli manager
Home-page: https://gitlab.com/tiagocoutinho/tangoctl
Author: Jose Tiago Macara Coutinho
Author-email: coutinhotiago@gmail.com
License: MIT license
Keywords: tangoctl
Platform: UNKNOWN
Classifier: Development Status :: 2 - Pre-Alpha
Classifier: Intended Audience :: Developers
Classifier: License :: OSI Approved :: MIT License
Classifier: Natural Language :: English
Classifier: Programming Language :: Python :: 2
Classifier: Programming Language :: Python :: 3
Requires-Dist: pytango
Requires-Dist: click
Requires-Dist: treelib
Requires-Dist: gevent
Requires-Dist: tabulate
Requires-Dist: six
